pcrunner/__init__.py
pcrunner/configuration.py
pcrunner/daemon.py
pcrunner/exception.py
pcrunner/main.py
pcrunner/windows_service.py
pcrunner/data/empty
pcrunner/etc/commands.txt
pcrunner/etc/commands.yml
pcrunner/etc/pcrunner.yml
pcrunner/init/pcrunner
pcrunner/scripts/check_dummy.py
pcrunner/scripts/pcr.py
pcrunner/scripts/run_check.py
pcrunner/systemd/pcrunner.service
pcrunner-1.0.3.data/scripts/check_dummy.py
pcrunner-1.0.3.data/scripts/run_check.py
pcrunner-1.0.3.dist-info/LICENSE.txt
pcrunner-1.0.3.dist-info/METADATA
pcrunner-1.0.3.dist-info/WHEEL
pcrunner-1.0.3.dist-info/entry_points.txt
pcrunner-1.0.3.dist-info/top_level.txt
pcrunner-1.0.3.dist-info/RECORD
