Metadata-Version: 2.1
Name: pcrunner
Version: 1.0.3
Summary: A module for running Passive Nagios/Icinga Checks
Home-page: https://github.com/maartenq/pcrunner
Author: Maarten
Author-email: ikmaarten@gmail.com
License: ISC
Project-URL: Bug Tracker, https://github.com/maartenq/pcrunner/issues
Project-URL: Changelog, https://github.com/maartenq/pcrunner/blob/main/HISTORY.rst
Keywords: pcrunner
Classifier: Development Status :: 5 - Production/Stable
Classifier: Environment :: Console
Classifier: Intended Audience :: System Administrators
Classifier: License :: OSI Approved :: ISC License (ISCL)
Classifier: License :: OSI Approved :: MIT License
Classifier: Natural Language :: English
Classifier: Operating System :: POSIX
Classifier: Programming Language :: Python :: 3
Classifier: Programming Language :: Python :: 3 :: Only
Classifier: Topic :: Documentation :: Sphinx
Classifier: Topic :: System :: Monitoring
Classifier: Topic :: System :: Systems Administration
Requires-Python: >=3.8
License-File: LICENSE.txt
Requires-Dist: PyYAML
Provides-Extra: dev
Requires-Dist: Sphinx ; extra == 'dev'
Requires-Dist: black ; extra == 'dev'
Requires-Dist: build ; extra == 'dev'
Requires-Dist: coverage ; extra == 'dev'
Requires-Dist: pre-commit ; extra == 'dev'
Requires-Dist: pytest ; extra == 'dev'
Requires-Dist: pytest-cov ; extra == 'dev'
Requires-Dist: responses ; extra == 'dev'
Requires-Dist: sphinx-rtd-theme ; extra == 'dev'
Requires-Dist: tox ; extra == 'dev'
Requires-Dist: twine ; extra == 'dev'
Provides-Extra: docs
Requires-Dist: Sphinx ; extra == 'docs'
Requires-Dist: sphinx-rtd-theme ; extra == 'docs'
Provides-Extra: test
Requires-Dist: pytest ; extra == 'test'
Requires-Dist: pytest-cov ; extra == 'test'
